setup.py
common_pos_ex_forex_next3/__init__.py
common_pos_ex_forex_next3/common_pos_ex_forex_next3.py
common_pos_ex_forex_next3.egg-info/PKG-INFO
common_pos_ex_forex_next3.egg-info/SOURCES.txt
common_pos_ex_forex_next3.egg-info/dependency_links.txt
common_pos_ex_forex_next3.egg-info/not-zip-safe
common_pos_ex_forex_next3.egg-info/top_level.txt