Metadata-Version: 1.0
Name: common-pos-ex-forex-next3
Version: 1.49
Summary: common_pos_ex_forex_next3
Home-page: UNKNOWN
Author: omid
Author-email: UNKNOWN
License: UNKNOWN
Platform: UNKNOWN
